MANIFEST.in
README.rst
setup.py
dnaconverter2/__init__.py
dnaconverter2/dna.py
dnaconverter2.egg-info/PKG-INFO
dnaconverter2.egg-info/SOURCES.txt
dnaconverter2.egg-info/dependency_links.txt
dnaconverter2.egg-info/entry_points.txt
dnaconverter2.egg-info/top_level.txt
dnaconverter2/data/huff3.dict