Metadata-Version: 1.0
Name: dnaconverter2
Version: 1.0.2
Summary: an algorithm to encode any file into a sequence of ACGT
Home-page: UNKNOWN
Author: Anshul Khanna
Author-email: anshul17khanna@gmail.com
License: MIT
Keywords: dnaconverter
Platform: UNKNOWN
